test/__init__.py
test/test_embeddings.py
test/test_initializers.py
test/test_metrics.py
test/test_mpo.py
test/test_mps.py
test/test_smpo.py
tn4ml/__init__.py
tn4ml/embeddings.py
tn4ml/eval.py
tn4ml/initializers.py
tn4ml/metrics.py
tn4ml/strategy.py
tn4ml/util.py
tn4ml/models/__init__.py
tn4ml/models/model.py
tn4ml/models/mpo.py
tn4ml/models/mps.py
tn4ml/models/smpo.py
tn4ml/models/tn.py
tn4ml-1.0.5.dist-info/LICENSE
tn4ml-1.0.5.dist-info/METADATA
tn4ml-1.0.5.dist-info/WHEEL
tn4ml-1.0.5.dist-info/top_level.txt
tn4ml-1.0.5.dist-info/RECORD
