Metadata-Version: 2.2
Name: tn4ml
Version: 1.0.5
Summary: Tensor Networks for Machine Learning
Home-page: https://github.com/bsc-quantic/tn4ml/tree/master
Author: Ema Puljak, Sergio Sanchez Ramirez, Sergi Masot Llima, Jofre Vallès-Muns
License: MIT
Classifier: License :: OSI Approved :: MIT License
Classifier: Programming Language :: Python :: 3
Classifier: Programming Language :: Python :: 3.8
Classifier: Programming Language :: Python :: 3.9
Classifier: Programming Language :: Python :: 3.10
Classifier: Programming Language :: Python :: 3.11
Classifier: Programming Language :: Python :: 3.12
Requires-Python: >=3.8
License-File: LICENSE
Requires-Dist: autoray>=0.3.0
Requires-Dist: dask
Requires-Dist: funcy
Requires-Dist: numpy
Requires-Dist: opt_einsum
Requires-Dist: quimb>=1.4.1
Requires-Dist: jaxlib
Requires-Dist: jax
Requires-Dist: optax
Requires-Dist: flax
Requires-Dist: pandas
Requires-Dist: nevergrad
Requires-Dist: chocolate
Requires-Dist: baytune
Requires-Dist: optuna
Requires-Dist: scikit-optimize
Requires-Dist: kahypar
Provides-Extra: docs
Requires-Dist: sphinx<8.0.0; extra == "docs"
Requires-Dist: sphinx-book-theme; extra == "docs"
Requires-Dist: ipykernel; extra == "docs"
Requires-Dist: nbsphinx; extra == "docs"
Requires-Dist: myst-parser; extra == "docs"
Requires-Dist: sphinxcontrib-bibtex; extra == "docs"
Requires-Dist: sphinxcontrib-devhelp; extra == "docs"
Requires-Dist: sphinxcontrib-htmlhelp; extra == "docs"
Requires-Dist: sphinxcontrib-jsmath; extra == "docs"
Requires-Dist: sphinxcontrib-qthelp; extra == "docs"
Requires-Dist: sphinxcontrib-serializinghtml; extra == "docs"
Requires-Dist: sphinx-rtd-theme; extra == "docs"
Requires-Dist: sphinx-copybutton; extra == "docs"
Requires-Dist: sphinx-gallery; extra == "docs"
Requires-Dist: tensorflow; extra == "docs"
Requires-Dist: matplotlib; extra == "docs"
Provides-Extra: test
Requires-Dist: pytest; extra == "test"
Provides-Extra: examples
Requires-Dist: matplotlib; extra == "examples"
Requires-Dist: scikit-learn; extra == "examples"
Requires-Dist: argparse; extra == "examples"
Requires-Dist: tensorflow; extra == "examples"
Requires-Dist: seaborn; extra == "examples"
Dynamic: author
Dynamic: classifier
Dynamic: description
Dynamic: description-content-type
Dynamic: home-page
Dynamic: license
Dynamic: provides-extra
Dynamic: requires-dist
Dynamic: requires-python
Dynamic: summary
